LICENSE.txt
MANIFEST.in
README.rst
setup.py
django_email_login_fc.egg-info/PKG-INFO
django_email_login_fc.egg-info/SOURCES.txt
django_email_login_fc.egg-info/dependency_links.txt
django_email_login_fc.egg-info/not-zip-safe
django_email_login_fc.egg-info/top_level.txt
email_login/__init__.py
email_login/adminsite.py
email_login/auth_backend.py
email_login/forms.py
email_login/models.py
email_login/tests.py
email_login/urls.py
email_login/useradmin.py
email_login/locale/nl/LC_MESSAGES/django.mo
email_login/locale/nl/LC_MESSAGES/django.po
email_login/locale/ru/LC_MESSAGES/django.mo
email_login/locale/ru/LC_MESSAGES/django.po
email_login/templates/email_login/base.html
email_login/templates/email_login/login.html
email_login/templates/registration/password_reset_email.html