Metadata-Version: 1.0
Name: django-email-login-fc
Version: 0.3.2
Summary: A Django application that enables you to have your users use their email address instead of their username
Home-page: https://github.com/futurecolors/django-email-login
Author: Ilya Baryshev
Author-email: baryshev@futurecolors.ru
License: MIT License
Platform: UNKNOWN
Classifier: Programming Language :: Python
Classifier: License :: OSI Approved :: MIT License
Classifier: Operating System :: OS Independent
Classifier: Development Status :: 4 - Beta
Classifier: Environment :: Web Environment
Classifier: Framework :: Django
Classifier: Intended Audience :: Developers
Classifier: Topic :: Software Development :: Libraries :: Python Modules
